setup.py
ojii/__init__.py
ojii/admin.py
ojii/fields.py
ojii/models.py
ojii/templatetags/__init__.py
ojii/templatetags/ojii_filters.py
ojii/templatetags/ojii_tags.py
ojii/utils/__init__.py
ojii/utils/actions.py
ojii/utils/cache.py
ojii/utils/cmsplugin.py
ojii/utils/datastructures.py
ojii/utils/datetime.py
ojii/utils/debug.py
ojii/utils/decorators.py
ojii/utils/findmemcached.py
ojii/utils/image.py
ojii/utils/lxmlparse.py
ojii/utils/manager.py
ojii/utils/simplelock.py
ojii/utils/slug.py
ojii/utils/unittest.py
ojii_utils.egg-info/PKG-INFO
ojii_utils.egg-info/SOURCES.txt
ojii_utils.egg-info/dependency_links.txt
ojii_utils.egg-info/not-zip-safe
ojii_utils.egg-info/top_level.txt