Metadata-Version: 1.0
Name: ojii-utils
Version: 0.1.0
Summary: Some utilities I wrote
Home-page: http://github.com/ojii/ojii-utils
Author: Jonas Obrist
Author-email: jonas.obrist@divio.ch
License: UNKNOWN
Platform: UNKNOWN
